amsdal_framework/__about__.py
amsdal_framework/errors.pyi
amsdal_framework/__init__.pyi
amsdal_framework/__about__.pyi
amsdal_framework/__init__.py
amsdal_framework/py.typed
amsdal_framework/manager.cpython-311-x86_64-linux-gnu.so
amsdal_framework/manager.pyi
amsdal_framework/errors.py
amsdal_framework/Third-Party Materials - AMSDAL Dependencies - License Notices.md
amsdal_framework/services/transaction_execution.pyi
amsdal_framework/services/transaction_execution.cpython-311-x86_64-linux-gnu.so
amsdal_framework/services/__init__.cpython-311-x86_64-linux-gnu.so
amsdal_framework/services/__init__.pyi
amsdal_framework/schemas/manager.py
amsdal_framework/schemas/__init__.pyi
amsdal_framework/schemas/__init__.py
amsdal_framework/schemas/manager.cpython-311-x86_64-linux-gnu.so
amsdal_framework/schemas/manager.pyi
amsdal_framework/schemas/core/fixture/model.json
amsdal_framework/schemas/core/class_object/model.json
amsdal_framework/schemas/core/class_object/properties/display_name.py
amsdal_framework/schemas/core/document/model.json
amsdal_framework/schemas/core/validator/model.json
amsdal_framework/schemas/core/class_property/model.json
amsdal_framework/schemas/core/option/model.json
amsdal_framework/schemas/core/file/model.json
amsdal_framework/schemas/core/file/properties/to_file.py
amsdal_framework/schemas/core/file/properties/from_file.py
amsdal_framework/schemas/core/file/properties/validate_data.py
amsdal_framework/schemas/core/file/properties/mimetype.py
amsdal_framework/schemas/core/file/hooks/pre_update.py
amsdal_framework/schemas/core/file/hooks/pre_create.py
amsdal_framework/schemas/types/binary/model.json
amsdal_framework/schemas/types/dictionary/model.json
amsdal_framework/schemas/types/object/model.json
amsdal_framework/schemas/types/anything/model.json
amsdal_framework/schemas/types/string/model.json
amsdal_framework/schemas/types/array/model.json
amsdal_framework/schemas/types/number/model.json
amsdal_framework-0.0.11.dist-info/METADATA
amsdal_framework-0.0.11.dist-info/WHEEL
amsdal_framework-0.0.11.dist-info/RECORD
amsdal_framework-0.0.11.dist-info/LICENSE.txt
amsdal_framework-0.0.11.dist-info/top_level.txt
