Metadata-Version: 2.1
Name: amsdal_framework
Version: 0.0.11
Summary: AMSDAL
License: AMSDAL End User License Agreement
Project-URL: Documentation, https://pypi.org/project/amsdal-framework/#readme
Project-URL: Issues, https://pypi.org/project/amsdal-framework/
Project-URL: Source, https://pypi.org/project/amsdal-framework/
Classifier: Development Status :: 4 - Beta
Classifier: Programming Language :: Python
Classifier: Programming Language :: Python :: 3.10
Classifier: Programming Language :: Python :: 3.11
Classifier: Programming Language :: Python :: Implementation :: CPython
Classifier: Programming Language :: Python :: Implementation :: PyPy
Requires-Python: >=3.10
License-File: LICENSE.txt
Requires-Dist: pydantic ==2.3.0
Requires-Dist: pydantic-settings ==2.0.3
Requires-Dist: PyJWT ==2.8.0
Requires-Dist: cryptography ==40.0.2
Requires-Dist: httpx ==0.25.0
Requires-Dist: bcrypt ==4.0.1
Requires-Dist: amsdal-utils ==0.0.*
Requires-Dist: amsdal-data[iceberg-lakehouse] ==0.0.*
Requires-Dist: amsdal-models ==0.0.*
Provides-Extra: cli
Requires-Dist: amsdal-cli ==0.0.* ; extra == 'cli'
Provides-Extra: redis-lock
Requires-Dist: amsdal-data[redis-lock] ==0.0.* ; extra == 'redis-lock'
Provides-Extra: server
Requires-Dist: amsdal-server ==0.0.* ; extra == 'server'
